Workbook

Sheet Summary
A1: ErgoMatrix Deskscape – Costing Summary (every cost shown separately)
A2: Classic finish · free shipping · woodworker paid a fixed rate per piece · profit is before ads, photos and GST registration
A4: Item | B4: Selling price | C4: Woodworker rate | D4: Speed Post to Pune | E4: Finishing (oil, wax, sandpaper) | F4: Packing in Pune | G4: Shiprocket to customer (incl. GST) | H4: Payment fees & returns | I4: Total cost | J4: Profit | K4: Margin | L4: Profit after ad cost
A5: ='Per Item'!A9 -> Laptop stand | B5: ='Per Item'!B9 -> ₹699 | C5: ='Per Item'!C9 -> ₹110 | D5: ='Per Item'!D9 -> ₹134 | E5: ='Per Item'!E9 -> ₹20 | F5: ='Per Item'!F9 -> ₹58 | G5: ='Per Item'!H9 -> ₹153 | H5: ='Per Item'!I9 -> ₹42 | I5: ='Per Item'!J9 -> ₹517 | J5: ='Per Item'!K9 -> ₹182 | K5: ='Per Item'!L9 -> 26.1% | L5: ='Per Item'!M9 -> ₹32
A6: ='Per Item'!A10 -> Headphone stand | B6: ='Per Item'!B10 -> ₹549 | C6: ='Per Item'!C10 -> ₹90 | D6: ='Per Item'!D10 -> ₹83 | E6: ='Per Item'!E10 -> ₹20 | F6: ='Per Item'!F10 -> ₹43 | G6: ='Per Item'!H10 -> ₹106 | H6: ='Per Item'!I10 -> ₹33 | I6: ='Per Item'!J10 -> ₹376 | J6: ='Per Item'!K10 -> ₹173 | K6: ='Per Item'!L10 -> 31.6% | L6: ='Per Item'!M10 -> ₹23
A7: ='Per Item'!A11 -> Tablet stand | B7: ='Per Item'!B11 -> ₹449 | C7: ='Per Item'!C11 -> ₹70 | D7: ='Per Item'!D11 -> ₹67 | E7: ='Per Item'!E11 -> ₹18 | F7: ='Per Item'!F11 -> ₹43 | G7: ='Per Item'!H11 -> ₹106 | H7: ='Per Item'!I11 -> ₹27 | I7: ='Per Item'!J11 -> ₹331 | J7: ='Per Item'!K11 -> ₹118 | K7: ='Per Item'!L11 -> 26.3% | L7: ='Per Item'!M11 -> (₹32)
A8: ='Per Item'!A12 -> Mobile stand | B8: ='Per Item'!B12 -> ₹349 | C8: ='Per Item'!C12 -> ₹60 | D8: ='Per Item'!D12 -> ₹33 | E8: ='Per Item'!E12 -> ₹15 | F8: ='Per Item'!F12 -> ₹25 | G8: ='Per Item'!H12 -> ₹59 | H8: ='Per Item'!I12 -> ₹21 | I8: ='Per Item'!J12 -> ₹213 | J8: ='Per Item'!K12 -> ₹136 | K8: ='Per Item'!L12 -> 38.9% | L8: ='Per Item'!M12 -> (₹14)
A9: ='Per Item'!A13 -> Cable holder | B9: ='Per Item'!B13 -> ₹299 | C9: ='Per Item'!C13 -> ₹60 | D9: ='Per Item'!D13 -> ₹25 | E9: ='Per Item'!E13 -> ₹12 | F9: ='Per Item'!F13 -> ₹25 | G9: ='Per Item'!H13 -> ₹59 | H9: ='Per Item'!I13 -> ₹18 | I9: ='Per Item'!J13 -> ₹199 | J9: ='Per Item'!K13 -> ₹100 | K9: ='Per Item'!L13 -> 33.5% | L9: ='Per Item'!M13 -> (₹50)
A10: One of each | B10: =SUM(B5:B9) -> ₹2,345 | C10: =SUM(C5:C9) -> ₹390 | D10: =SUM(D5:D9) -> ₹342 | E10: =SUM(E5:E9) -> ₹85 | F10: =SUM(F5:F9) -> ₹194 | G10: =SUM(G5:G9) -> ₹484 | H10: =SUM(H5:H9) -> ₹141 | I10: =SUM(I5:I9) -> ₹1,636 | J10: =SUM(J5:J9) -> ₹709 | K10: =IF(B10=0,0,J10/B10) -> 30.2% | L10: =SUM(L5:L9) -> (₹41)
A12: Bundle | B12: Selling price | C12: Woodworker rate | D12: Speed Post to Pune | E12: Finishing (oil, wax, sandpaper) | F12: Packing in Pune | G12: Shiprocket to customer (incl. GST) | H12: Payment fees & returns | I12: Total cost | J12: Profit | K12: Margin | L12: Profit after ad cost
A13: =Bundles!A4 -> Work-from-home set (laptop + mobile + cable holder) | B13: =Bundles!B4 -> ₹1,199 | C13: =Bundles!C4 -> ₹230 | D13: =Bundles!D4 -> ₹192 | E13: =Bundles!E4 -> ₹47 | F13: =Bundles!F4 -> ₹70 | G13: =Bundles!H4 -> ₹201 | H13: =Bundles!I4 -> ₹72 | I13: =Bundles!J4 -> ₹812 | J13: =Bundles!K4 -> ₹387 | K13: =Bundles!L4 -> 32.3% | L13: =Bundles!M4 -> ₹237
A14: =Bundles!A5 -> Full set (all 5 items) | B14: =Bundles!B5 -> ₹2,299 | C14: =Bundles!C5 -> ₹390 | D14: =Bundles!D5 -> ₹342 | E14: =Bundles!E5 -> ₹85 | F14: =Bundles!F5 -> ₹110 | G14: =Bundles!H5 -> ₹295 | H14: =Bundles!I5 -> ₹138 | I14: =Bundles!J5 -> ₹1,360 | J14: =Bundles!K5 -> ₹939 | K14: =Bundles!L5 -> 40.8% | L14: =Bundles!M5 -> ₹789
A16: Caveats
A17: • Courier rates were re-checked – see 'Rate Check'. 18% GST is included in Speed Post and Shiprocket figures.
A18: • Woodworker rates, weights, finishing and packing are estimates, not quotes. Update the blue cells on 'Assumptions' with real figures.
A19: • Not included: ads/photos (see last column), samples, COD fees, return shipping, GST registration, your own time.
A20: • On paid ads, the tablet stand, mobile stand and cable holder are break-even or loss-making – sell them mainly in bundles.

Sheet Assumptions
A1: ErgoMatrix Deskscape – Assumptions (edit blue cells on yellow)
A2: All other sheets recalculate from this sheet. Figures marked 'estimate' are my guesses, not quotes.
A3: Rate / cost input | B3: Value | C3: Basis
A4: Speed Post – first 500 g (Srinagar→Pune, '>2,000 km' slab, ex-GST) | B4: 90 | C4: Old India Post tariff table: 201–500 g, >2,000 km = ₹90 (conservative slab; verify with India Post calculator)
A5: Speed Post – each extra 500 g (ex-GST) | B5: 50 | C5: Up to ₹50 per extra 500 g above 2,000 km (Shiprocket blog on Speed Post charges)
A6: GST on courier / postal charges | B6: 0.18 | C6: Tariffs are quoted excluding taxes; 18% GST assumed
A7: Shiprocket – first 500 g, Rest of India (ex-GST) | B7: 50 | C7: Indicative ROI retail band ₹45–70 (ShipPrime, Jul 2026); aggregator entry rates can be lower
A8: Shiprocket – each extra 500 g (ex-GST) | B8: 40 | C8: ShipPrime indicative ROI rate card example: ₹50 base + ₹40 per extra 500 g
A9: Payment fees + returns/breakage (% of selling price) | B9: 0.06 | C9: Estimate: ~2% gateway + ~4% returns/breakage
A10: Packed-weight multiplier for woodworker's consignment | B10: 1.2 | C10: Estimate: his cartons/wrap add ~20% to item weight
A11: Ad cost per order (sensitivity only) | B11: 150 | C11: Estimate: ₹150–250 per order from Instagram ads
A12: Courier weight slab size (kg) | B12: 0.5 | C12: Both Speed Post and Shiprocket bill in 500 g slabs
A14: Per-item inputs (Classic finish)
A15: Item | B15: Selling price | C15: Woodworker fixed rate | D15: Item weight (kg) | E15: Packed weight to customer (kg) | F15: Finishing cost (oil, wax, sandpaper) | G15: Packing cost in Pune (box, wrap, tape, card)
A16: Laptop stand | B16: 699 | C16: 110 | D16: 0.8 | E16: 1.1 | F16: 20 | G16: 58
A17: Headphone stand | B17: 549 | C17: 90 | D17: 0.5 | E17: 0.7 | F17: 20 | G17: 43
A18: Tablet stand | B18: 449 | C18: 70 | D18: 0.4 | E18: 0.55 | F18: 18 | G18: 43
A19: Mobile stand | B19: 349 | C19: 60 | D19: 0.2 | E19: 0.35 | F19: 15 | G19: 25
A20: Cable holder | B20: 299 | C20: 60 | D20: 0.15 | E20: 0.3 | F20: 12 | G20: 25
A21: Notes: selling prices are my suggested Classic prices; woodworker rates are my suggestion, not his quote; weights, finishing and packing are estimates. Replace with real figures after your sample batch.
A23: Bundle inputs
A24: Bundle | B24: Selling price | C24: Packing cost in Pune | D24: Packed weight to customer (kg)
A25: Work-from-home set (laptop + mobile + cable holder) | B25: 1199 | C25: 70 | D25: 1.65
A26: Full set (all 5 items) | B26: 2299 | C26: 110 | D26: 2.85

Sheet Per Item
A1: Per-item costing – Classic finish, one item per order, free shipping
A3: Inbound consignment (1 of each item) – total packed weight (kg) | B3: =SUM(Assumptions!D16:D20)*Assumptions!B10 -> 2.46
A4: Courier slabs (500 g) | B4: =ROUNDUP(B3/Assumptions!B12,0) -> 5
A5: Speed Post cost for the consignment (incl. GST) | B5: =(Assumptions!B4+(B4-1)*Assumptions!B5)*(1+Assumptions!B6) -> ₹342
A8: Item | B8: Selling price | C8: Woodworker rate | D8: Speed Post to Pune (share by weight) | E8: Finishing | F8: Packing in Pune | G8: Shiprocket slabs (500 g) | H8: Shiprocket to customer (incl. GST) | I8: Fees & returns | J8: Total cost | K8: Profit | L8: Margin | M8: Profit after ad cost
A9: =Assumptions!A16 -> Laptop stand | B9: =Assumptions!B16 -> ₹699 | C9: =Assumptions!C16 -> ₹110 | D9: =$B$5*Assumptions!D16/SUM(Assumptions!$D$16:$D$20) -> ₹134 | E9: =Assumptions!F16 -> ₹20 | F9: =Assumptions!G16 -> ₹58 | G9: =ROUNDUP(Assumptions!E16/Assumptions!$B$12,0) -> 3 | H9: =(Assumptions!$B$7+(G9-1)*Assumptions!$B$8)*(1+Assumptions!$B$6) -> ₹153 | I9: =B9*Assumptions!$B$9 -> ₹42 | J9: =C9+D9+E9+F9+H9+I9 -> ₹517 | K9: =B9-J9 -> ₹182 | L9: =IF(B9=0,0,K9/B9) -> 26.1% | M9: =K9-Assumptions!$B$11 -> ₹32
A10: =Assumptions!A17 -> Headphone stand | B10: =Assumptions!B17 -> ₹549 | C10: =Assumptions!C17 -> ₹90 | D10: =$B$5*Assumptions!D17/SUM(Assumptions!$D$16:$D$20) -> ₹83 | E10: =Assumptions!F17 -> ₹20 | F10: =Assumptions!G17 -> ₹43 | G10: =ROUNDUP(Assumptions!E17/Assumptions!$B$12,0) -> 2 | H10: =(Assumptions!$B$7+(G10-1)*Assumptions!$B$8)*(1+Assumptions!$B$6) -> ₹106 | I10: =B10*Assumptions!$B$9 -> ₹33 | J10: =C10+D10+E10+F10+H10+I10 -> ₹376 | K10: =B10-J10 -> ₹173 | L10: =IF(B10=0,0,K10/B10) -> 31.6% | M10: =K10-Assumptions!$B$11 -> ₹23
A11: =Assumptions!A18 -> Tablet stand | B11: =Assumptions!B18 -> ₹449 | C11: =Assumptions!C18 -> ₹70 | D11: =$B$5*Assumptions!D18/SUM(Assumptions!$D$16:$D$20) -> ₹67 | E11: =Assumptions!F18 -> ₹18 | F11: =Assumptions!G18 -> ₹43 | G11: =ROUNDUP(Assumptions!E18/Assumptions!$B$12,0) -> 2 | H11: =(Assumptions!$B$7+(G11-1)*Assumptions!$B$8)*(1+Assumptions!$B$6) -> ₹106 | I11: =B11*Assumptions!$B$9 -> ₹27 | J11: =C11+D11+E11+F11+H11+I11 -> ₹331 | K11: =B11-J11 -> ₹118 | L11: =IF(B11=0,0,K11/B11) -> 26.3% | M11: =K11-Assumptions!$B$11 -> (₹32)
A12: =Assumptions!A19 -> Mobile stand | B12: =Assumptions!B19 -> ₹349 | C12: =Assumptions!C19 -> ₹60 | D12: =$B$5*Assumptions!D19/SUM(Assumptions!$D$16:$D$20) -> ₹33 | E12: =Assumptions!F19 -> ₹15 | F12: =Assumptions!G19 -> ₹25 | G12: =ROUNDUP(Assumptions!E19/Assumptions!$B$12,0) -> 1 | H12: =(Assumptions!$B$7+(G12-1)*Assumptions!$B$8)*(1+Assumptions!$B$6) -> ₹59 | I12: =B12*Assumptions!$B$9 -> ₹21 | J12: =C12+D12+E12+F12+H12+I12 -> ₹213 | K12: =B12-J12 -> ₹136 | L12: =IF(B12=0,0,K12/B12) -> 38.9% | M12: =K12-Assumptions!$B$11 -> (₹14)
A13: =Assumptions!A20 -> Cable holder | B13: =Assumptions!B20 -> ₹299 | C13: =Assumptions!C20 -> ₹60 | D13: =$B$5*Assumptions!D20/SUM(Assumptions!$D$16:$D$20) -> ₹25 | E13: =Assumptions!F20 -> ₹12 | F13: =Assumptions!G20 -> ₹25 | G13: =ROUNDUP(Assumptions!E20/Assumptions!$B$12,0) -> 1 | H13: =(Assumptions!$B$7+(G13-1)*Assumptions!$B$8)*(1+Assumptions!$B$6) -> ₹59 | I13: =B13*Assumptions!$B$9 -> ₹18 | J13: =C13+D13+E13+F13+H13+I13 -> ₹199 | K13: =B13-J13 -> ₹100 | L13: =IF(B13=0,0,K13/B13) -> 33.5% | M13: =K13-Assumptions!$B$11 -> (₹50)
A14: One of each | B14: =SUM(B9:B13) -> ₹2,345 | C14: =SUM(C9:C13) -> ₹390 | D14: =SUM(D9:D13) -> ₹342 | E14: =SUM(E9:E13) -> ₹85 | F14: =SUM(F9:F13) -> ₹194 | H14: =SUM(H9:H13) -> ₹484 | I14: =SUM(I9:I13) -> ₹141 | J14: =SUM(J9:J13) -> ₹1,636 | K14: =SUM(K9:K13) -> ₹709 | L14: =IF(B14=0,0,K14/B14) -> 30.2% | M14: =SUM(M9:M13) -> (₹41)
A16: Column M subtracts the ad cost per order from Assumptions!B11. Negative = loses money if the order came from paid ads.

Sheet Bundles
A1: Bundle costing – one parcel to the customer
A3: Bundle | B3: Selling price | C3: Woodworker rate | D3: Speed Post to Pune (share) | E3: Finishing | F3: Packing in Pune | G3: Shiprocket slabs (500 g) | H3: Shiprocket to customer (incl. GST) | I3: Fees & returns | J3: Total cost | K3: Profit | L3: Margin | M3: Profit after ad cost
A4: =Assumptions!A25 -> Work-from-home set (laptop + mobile + cable holder) | B4: =Assumptions!B25 -> ₹1,199 | C4: ='Per Item'!C9+'Per Item'!C12+'Per Item'!C13 -> ₹230 | D4: ='Per Item'!D9+'Per Item'!D12+'Per Item'!D13 -> ₹192 | E4: ='Per Item'!E9+'Per Item'!E12+'Per Item'!E13 -> ₹47 | F4: =Assumptions!C25 -> ₹70 | G4: =ROUNDUP(Assumptions!D25/Assumptions!$B$12,0) -> 4 | H4: =(Assumptions!$B$7+(G4-1)*Assumptions!$B$8)*(1+Assumptions!$B$6) -> ₹201 | I4: =B4*Assumptions!$B$9 -> ₹72 | J4: =C4+D4+E4+F4+H4+I4 -> ₹812 | K4: =B4-J4 -> ₹387 | L4: =IF(B4=0,0,K4/B4) -> 32.3% | M4: =K4-Assumptions!$B$11 -> ₹237
A5: =Assumptions!A26 -> Full set (all 5 items) | B5: =Assumptions!B26 -> ₹2,299 | C5: ='Per Item'!C9+'Per Item'!C10+'Per Item'!C11+'Per Item'!C12+'Per Item'!C13 -> ₹390 | D5: ='Per Item'!D9+'Per Item'!D10+'Per Item'!D11+'Per Item'!D12+'Per Item'!D13 -> ₹342 | E5: ='Per Item'!E9+'Per Item'!E10+'Per Item'!E11+'Per Item'!E12+'Per Item'!E13 -> ₹85 | F5: =Assumptions!C26 -> ₹110 | G5: =ROUNDUP(Assumptions!D26/Assumptions!$B$12,0) -> 6 | H5: =(Assumptions!$B$7+(G5-1)*Assumptions!$B$8)*(1+Assumptions!$B$6) -> ₹295 | I5: =B5*Assumptions!$B$9 -> ₹138 | J5: =C5+D5+E5+F5+H5+I5 -> ₹1,360 | K5: =B5-J5 -> ₹939 | L5: =IF(B5=0,0,K5/B5) -> 40.8% | M5: =K5-Assumptions!$B$11 -> ₹789
A7: Compare: selling the same items separately (from 'Per Item')
A8: Work-from-home items sold separately – total profit | B8: ='Per Item'!K9+'Per Item'!K12+'Per Item'!K13 -> ₹418
A9: Full set items sold separately – total profit | B9: ='Per Item'!K14 -> ₹709

Sheet Rate Check
A1: Rate re-check (searched 19 Oct 2026)
A3: Item | B3: What I said before | C3: What sources show now | D3: Used in this workbook
A4: Speed Post, 1 kg, above 2,000 km | B4: ~₹130–180 (first kg) plus ~₹100 per extra kg | C4: ClickPost: ₹130–140 per 1 kg. iThink: ₹170–180 first kg, then ~₹100–110/kg. Extra 500 g: up to ₹50 (Shiprocket blog). Tariffs exclude GST. | D4: ₹90 first 500 g + ₹50 per extra 500 g (=₹140 per kg) + 18% GST
A5: Speed Post distance slab | B5: Assumed '>2,000 km' | C5: Slab depends on distance. Srinagar–Pune is roughly 1,700 km in a straight line and more by road, so it may fall in the cheaper 1,001–2,000 km slab. Not confirmed. | D5: Higher slab used (conservative). Check pin-code to pin-code on India Post's calculator.
A6: Speed Post loss/damage cover | B6: Double the charges or ₹1,000 | C6: India Post: double the Speed Post charges or ₹1,000, whichever is less. | D6: Not costed – insure or use a courier with declared value for larger batches.
A7: Shiprocket, first 500 g (Rest of India) | B7: ₹70–125 per parcel | C7: ShipPrime (Jul 2026): ROI first 500 g ₹45–70; example ₹50 + ₹40 per extra 500 g. Aggregator entry rates start ~₹20–27 per 500 g. 18% GST extra. | D7: ₹50 + ₹40 per extra 500 g + 18% GST (=₹59 for 0.5 kg, ₹106 for 1 kg, ₹153 for 1.5 kg)
A8: Shiprocket extras not in model | B8: Not mentioned | C8: COD fee (e.g. ₹30–50 per order), return-to-origin charges, volumetric weight for big boxes, higher rates for J&K, North-East, Kerala and Himachal (Zone E). | D8: Excluded – raise the courier inputs if many orders are COD or remote.
A9: Packing boxes | B9: 5-ply box ₹7–36 | C9: IndiaMART listings: 5-ply corrugated boxes ₹7–36 each; a 500×300×250 mm 5-ply box ₹36; kraft bubble wrap roll 15 in × 100 m ₹400. | D9: Packing per item: ₹25–58 (box + wrap + tape + card) – estimate
A11: Sources: Shiprocket blog 'Speed Post charges'; iThink Logistics Speed Post guide; ClickPost India Post charges; India Post Speed Post Parcel page; ShipPrime shipping-cost guide (20 Jul 2026); IndiaMART packaging listings.
